<?xml version="1.0" encoding="UTF-8" ?>
<!DOCTYPE mapper PUBLIC "-//mybatis.org//DTD Mapper 3.0//EN" "http://mybatis.org/dtd/mybatis-3-mapper.dtd" >
<mapper namespace="com.dhc.dhc_xatrain.daos.SysMenuMapper" >
  <resultMap id="BaseResultMap" type="com.dhc.dhc_xatrain.mapper.SysMenu" >
    <!--
      WARNING - @mbggenerated
      This element is automatically generated by MyBatis Generator, do not modify.
      This element was generated on Wed Aug 07 11:36:21 CST 2019.
    -->
    <result column="menu_id" property="menuId" jdbcType="BIGINT" />
    <result column="parent_id" property="parentId" jdbcType="BIGINT" />
    <result column="menu_name" property="menuName" jdbcType="VARCHAR" />
    <result column="menu_url" property="menuUrl" jdbcType="VARCHAR" />
    <result column="type" property="type" jdbcType="VARCHAR" />
    <result column="icon" property="icon" jdbcType="VARCHAR" />
    <result column="isShow" property="isshow" jdbcType="VARCHAR" />
    <result column="order_num" property="orderNum" jdbcType="INTEGER" />
    <result column="menu_state" property="menuState" jdbcType="VARCHAR" />
  </resultMap>
  <insert id="insert" parameterType="com.dhc.dhc_xatrain.mapper.SysMenu" >
    <!--
      WARNING - @mbggenerated
      This element is automatically generated by MyBatis Generator, do not modify.
      This element was generated on Wed Aug 07 11:36:21 CST 2019.
    -->
    insert into sys_menu (menu_id, parent_id, menu_name, 
      menu_url, type, icon, 
      isShow, order_num, menu_state
      )
    values (#{menuId,jdbcType=BIGINT}, #{parentId,jdbcType=BIGINT}, #{menuName,jdbcType=VARCHAR}, 
      #{menuUrl,jdbcType=VARCHAR}, #{type,jdbcType=VARCHAR}, #{icon,jdbcType=VARCHAR}, 
      #{isshow,jdbcType=VARCHAR}, #{orderNum,jdbcType=INTEGER}, #{menuState,jdbcType=VARCHAR}
      )
  </insert>
  <select id="selectAll" resultMap="BaseResultMap" >
    <!--
      WARNING - @mbggenerated
      This element is automatically generated by MyBatis Generator, do not modify.
      This element was generated on Wed Aug 07 11:36:21 CST 2019.
    -->
    select menu_id, parent_id, menu_name, menu_url, type, icon, isShow, order_num, menu_state
    from sys_menu
  </select>
</mapper>